printtable.py
printtable_demo-0.0.1.dist-info/LICENSE
printtable_demo-0.0.1.dist-info/WHEEL
printtable_demo-0.0.1.dist-info/METADATA
printtable_demo-0.0.1.dist-info/RECORD
